clang_repl/__init__.py
clang_repl/__main__.py
clang_repl/clrepl.py
clang_repl/kernel.py
clang_repl-1.0.4.data/data/share/jupyter/kernels/clang_repl/kernel.json
clang_repl-1.0.4.dist-info/METADATA
clang_repl-1.0.4.dist-info/WHEEL
clang_repl-1.0.4.dist-info/licenses/LICENSE
clang_repl-1.0.4.dist-info/RECORD
