Metadata-Version: 2.4
Name: clang_repl
Version: 1.0.4
Summary: IPython kernel forwarding C++ cells to clang-repl
Project-URL: Homepage, https://github.com/pmanstet/clang_repl_kernel.git
Author-email: Paul Manstetten <paul.manstetten@tuwien.ac.at>
License-Expression: CC0-1.0
License-File: LICENSE
Requires-Python: >=3.11
Requires-Dist: ipykernel
Requires-Dist: jupyter-console
Requires-Dist: notebook
Requires-Dist: pexpect
